infi.rpc-0.2.9-py2.7-nspkg.pth
infi/rpc/__init__.py
infi/rpc/__version__.py
infi/rpc/errors.py
infi/rpc/json_traceback.py
infi/rpc/base/__init__.py
infi/rpc/base/client.py
infi/rpc/base/protocol.py
infi/rpc/base/server.py
infi/rpc/base/service.py
infi/rpc/base/utils.py
infi/rpc/zerorpc/__init__.py
infi/rpc/zerorpc/client.py
infi/rpc/zerorpc/server.py
infi.rpc-0.2.9.dist-info/LICENSE
infi.rpc-0.2.9.dist-info/METADATA
infi.rpc-0.2.9.dist-info/WHEEL
infi.rpc-0.2.9.dist-info/entry_points.txt
infi.rpc-0.2.9.dist-info/namespace_packages.txt
infi.rpc-0.2.9.dist-info/top_level.txt
infi.rpc-0.2.9.dist-info/RECORD
