Metadata-Version: 2.1
Name: infi.rpc
Version: 0.2.9
Summary: rpc
Home-page: https://github.com/Infinidat/infi.rpc
Author: Arnon Yaari
Author-email: arnony@infinidat.com
License: BSD
Platform: UNKNOWN
Classifier: Intended Audience :: Developers
Classifier: Intended Audience :: System Administrators
Classifier: License :: OSI Approved :: BSD License
Classifier: Operating System :: OS Independent
Classifier: Programming Language :: Python
Classifier: Programming Language :: Python :: 2
Classifier: Programming Language :: Python :: 3
Classifier: Topic :: Software Development :: Libraries :: Python Modules
Requires-Dist: infi.gevent-utils
Requires-Dist: infi.logging (>=0.4.1)
Requires-Dist: jsonpickle
Requires-Dist: Logbook (>=0.8)
Requires-Dist: setuptools
Requires-Dist: zerorpc
